blochify/__init__.py
blochify/_version.py
blochify/bloch.py
blochify-0.0.1.dist-info/METADATA
blochify-0.0.1.dist-info/WHEEL
blochify-0.0.1.dist-info/top_level.txt
blochify-0.0.1.dist-info/RECORD
