Metadata-Version: 2.1
Name: blochify
Version: 0.0.1
Summary: Blochify by BRAIN-LINK
Home-page: https://github.com/brain-link/blochify
Maintainer: Christoph Dinh
Maintainer-email: christoph.dinh@brain-link.de
License: BSD-licenced (3 clause)
Download-URL: https://github.com/brain-link/blochify
Project-URL: Source, https://github.com/brain-link/blochify/
Project-URL: Tracker, https://github.com/brain-link/blochify/issues/
Keywords: Blochify MRI
Platform: any
Classifier: Intended Audience :: Science/Research
Classifier: Intended Audience :: Developers
Classifier: License :: OSI Approved :: BSD License
Classifier: Topic :: Scientific/Engineering
Classifier: Programming Language :: Python :: 3
Classifier: Development Status :: 1 - Planning
Classifier: Operating System :: OS Independent
Requires-Python: >=3.7
Requires-Dist: numpy (==1.22.3)
Requires-Dist: tensorflow (==2.9.1)
